fileshash/__init__.py
fileshash/fileshash.py
fileshash/fileshash_cli.py
fileshash-0.1.1.dist-info/LICENSE
fileshash-0.1.1.dist-info/METADATA
fileshash-0.1.1.dist-info/WHEEL
fileshash-0.1.1.dist-info/entry_points.txt
fileshash-0.1.1.dist-info/top_level.txt
fileshash-0.1.1.dist-info/RECORD
