Metadata-Version: 2.1
Name: fileshash
Version: 0.1.1
Summary: Module and command-line tool that wraps around hashlib and zlib to facilitate generating checksums / hashes of files.
Home-page: https://github.com/mmore500/fileshash
Author: Matthew Andres Moreno
Author-email: m.more500@gmail.com
License: MIT
Platform: UNKNOWN
Classifier: Environment :: Console
Classifier: Intended Audience :: Developers
Classifier: Intended Audience :: End Users/Desktop
Classifier: License :: OSI Approved :: MIT License
Classifier: Programming Language :: Python
Classifier: Programming Language :: Python :: 2
Classifier: Programming Language :: Python :: 2.7
Classifier: Programming Language :: Python :: 3
Classifier: Programming Language :: Python :: 3.6
Classifier: Topic :: Software Development :: Libraries
Classifier: Topic :: Utilities
Requires-Dist: xxhash
